kidocare/models.py
kidocare/__init__.py
django_kidocare-1.0.dist-info/top_level.txt
django_kidocare-1.0.dist-info/METADATA
django_kidocare-1.0.dist-info/DESCRIPTION.rst
django_kidocare-1.0.dist-info/metadata.json
django_kidocare-1.0.dist-info/WHEEL
django_kidocare-1.0.dist-info/RECORD
