Metadata-Version: 2.0
Name: django-kidocare
Version: 1.0
Summary: Tools which help finding performance issues in Django projects
Home-page: http://kidosoft.pl
Author: Jakub STOLARSKI (Dryobates)
Author-email: jakub.stolarski@kidosoft.pl
License: beerware
Keywords: django monitoring performance
Platform: UNKNOWN
Classifier: Development Status :: 4 - Beta
Classifier: Environment :: Web Environment
Classifier: Intended Audience :: Developers
Classifier: License :: OSI Approved :: BSD License
Classifier: Operating System :: OS Independent
Classifier: Framework :: Django
Classifier: Programming Language :: Python
Classifier: Topic :: Utilities
